MANIFEST.in
README.md
pyunit
setup.cfg
setup.py
pytheons/__init__.py
pytheons.pyunit.egg-info/PKG-INFO
pytheons.pyunit.egg-info/SOURCES.txt
pytheons.pyunit.egg-info/dependency_links.txt
pytheons.pyunit.egg-info/requires.txt
pytheons.pyunit.egg-info/top_level.txt
pytheons/pyunit/__init__.py
pytheons/pyunit/config/logging.yaml
pytheons/pyunit/decorators/__init__.py
pytheons/pyunit/decorators/register.py
pytheons/pyunit/decorators/test.py
pytheons/pyunit/loaders/__init__.py
pytheons/pyunit/loaders/decorated_loader.py
pytheons/pyunit/suites/__init__.py
pytheons/pyunit/suites/test_runner.py
pytheons/pyunit/user_interface/__init__.py
pytheons/pyunit/user_interface/command_line_interface/__init__.py
pytheons/pyunit/user_interface/command_line_interface/command/__init__.py
pytheons/pyunit/user_interface/command_line_interface/command/abstract.py
pytheons/pyunit/user_interface/command_line_interface/command/config.py
pytheons/pyunit/user_interface/command_line_interface/command/run.py
pytheons/pyunit/user_interface/command_line_interface/output/__init__.py
pytheons/pyunit/user_interface/command_line_interface/output/logger.py