Metadata-Version: 2.1
Name: pytheons.pyunit
Version: 1.0.3
Summary: pyunit is wrapper for PyUnit (uniittest) framework with one important extension (syntax suger) by `@ test` decorator
Home-page: https://github.com/pytheons/pyunit
Author: pytheons
Author-email: maveilthain@gmail.com
License: MIT
Platform: UNKNOWN
